object_mother_pattern/__init__.py
object_mother_pattern/py.typed
object_mother_pattern/mothers/__init__.py
object_mother_pattern/mothers/base_mother.py
object_mother_pattern/mothers/name_mother.py
object_mother_pattern/mothers/text_mother.py
object_mother_pattern/mothers/dates/__init__.py
object_mother_pattern/mothers/dates/date/__init__.py
object_mother_pattern/mothers/dates/date/date_mother.py
object_mother_pattern/mothers/dates/date/string_date_mother.py
object_mother_pattern/mothers/dates/datetime/__init__.py
object_mother_pattern/mothers/dates/datetime/datetime_mother.py
object_mother_pattern/mothers/dates/datetime/string_datetime_mother.py
object_mother_pattern/mothers/identifiers/__init__.py
object_mother_pattern/mothers/identifiers/string_uuid_mother.py
object_mother_pattern/mothers/identifiers/uuid_mother.py
object_mother_pattern/mothers/primitives/__init__.py
object_mother_pattern/mothers/primitives/boolean_mother.py
object_mother_pattern/mothers/primitives/bytes_mother.py
object_mother_pattern/mothers/primitives/float_mother.py
object_mother_pattern/mothers/primitives/integer_mother.py
object_mother_pattern/mothers/primitives/string_mother.py
object_mother_pattern-2025.1.12.dist-info/METADATA
object_mother_pattern-2025.1.12.dist-info/WHEEL
object_mother_pattern-2025.1.12.dist-info/licenses/LICENSE.md
object_mother_pattern-2025.1.12.dist-info/RECORD
