Metadata-Version: 2.4
Name: object-mother-pattern
Version: 2025.1.12
Summary: The Object Mother Pattern is a Python package that simplifies and standardizes the creation of test objects.
Project-URL: Homepage, https://github.com/adriamontoto/object-mother-pattern
Project-URL: Repository, https://github.com/adriamontoto/object-mother-pattern
Project-URL: Issues, https://github.com/adriamontoto/object-mother-pattern/issues
Author: Adria Montoto
License-Expression: MIT
License-File: LICENSE.md
Keywords: development,object-mother,pattern,python,testing,tools,utilities,validation
Classifier: Intended Audience :: Developers
Classifier: License :: OSI Approved :: MIT License
Classifier: Operating System :: OS Independent
Classifier: Programming Language :: Python
Classifier: Programming Language :: Python :: 3
Classifier: Programming Language :: Python :: 3.11
Classifier: Programming Language :: Python :: 3.12
Classifier: Programming Language :: Python :: 3.13
Classifier: Typing :: Typed
Requires-Python: >=3.11
Requires-Dist: faker<34.0.0,>=28.0.0
Requires-Dist: python-dateutil<3.0.0,>=2.9.0
Provides-Extra: tests
Requires-Dist: coverage[toml]<8.0.0,>=7.0.0; extra == 'tests'
Requires-Dist: mypy[reports]<2.0.0,>=1.0.0; extra == 'tests'
Requires-Dist: pre-commit<5.0.0,>=3.0.0; extra == 'tests'
Requires-Dist: pytest-randomly<4.0.0,>=3.0.0; extra == 'tests'
Requires-Dist: pytest<9.0.0,>=8.0.0; extra == 'tests'
Requires-Dist: ruff<1.0.0,>=0.0.0; extra == 'tests'
Requires-Dist: types-python-dateutil<3.0.0,>=2.9.0.20241206; extra == 'tests'
